{
  "2753": {
    "inom": "SF-22-Y-C-I",
    "nome": "ICARAÍMA",
    "ring": [
      [
        -54.0,
        -23.5
      ],
      [
        -53.5,
        -23.5
      ],
      [
        -53.5,
        -23.0
      ],
      [
        -54.0,
        -23.0
      ],
      [
        -54.0,
        -23.5
      ]
    ],
    "edicoes": [
      2023,
      2021,
      1972
    ],
    "ordinal": 2,
    "utm_zona": 22,
    "epsg_pdf": "31982"
  },
  "2779": {
    "inom": "SF-22-Y-C-IV",
    "nome": "ALTÔNIA",
    "ring": [
      [
        -54.0,
        -24.0
      ],
      [
        -53.5,
        -24.0
      ],
      [
        -53.5,
        -23.5
      ],
      [
        -54.0,
        -23.5
      ],
      [
        -54.0,
        -24.0
      ]
    ],
    "edicoes": [
      2023,
      2021,
      1972
    ],
    "ordinal": 2,
    "utm_zona": 22,
    "epsg_pdf": "31982"
  },
  "2799": {
    "inom": "SG-21-X-B-III",
    "nome": "GUAÍRA",
    "ring": [
      [
        -54.5,
        -24.5
      ],
      [
        -54.0,
        -24.5
      ],
      [
        -54.0,
        -24.0
      ],
      [
        -54.5,
        -24.0
      ],
      [
        -54.5,
        -24.5
      ]
    ],
    "edicoes": [
      2021,
      1974,
      1972,
      1957
    ],
    "ordinal": 4,
    "utm_zona": 21,
    "epsg_pdf": "31981"
  }
}